{
  "scenario_name": "1942q4_german_1942q4_10_panzer_divisi_vs_british_1942q4_10th_armoured_d_squad",
  "quarter": "1942q4",
  "scenario_size": "squad",
  "points_target": 250,
  "generated_at": "2025-10-29T18:38:15.509436",
  "axis_force": {
    "nation": "german",
    "unit_name": "german_1942q4_10_panzer_division_toe",
    "experience": "veteran",
    "toe": {
      "tanks": {},
      "artillery": {
        "10.5cm leFH 18": {
          "count": 24,
          "caliber": "105mm"
        },
        "15cm sFH 18": {
          "count": 12,
          "caliber": "150mm"
        }
      },
      "anti_tank": {
        "7.5cm PaK 40": {
          "count": 18,
          "caliber": "75mm"
        },
        "5cm PaK 38": {
          "count": 9,
          "caliber": "50mm"
        }
      },
      "infantry": {},
      "vehicles": {}
    },
    "equipment_summary": {
      "total_tanks": 142,
      "total_artillery": 36,
      "total_at_guns": 27,
      "total_personnel": 13500
    }
  },
  "allied_force": {
    "nation": "british",
    "unit_name": "british_1942q4_10th_armoured_division_toe",
    "experience": "veteran",
    "toe": {
      "tanks": {},
      "artillery": {
        "Ordnance QF 25-pounder": {
          "count": 48,
          "caliber": "87.6mm"
        }
      },
      "anti_tank": {
        "Ordnance QF 6-pounder": {
          "count": 24,
          "caliber": "57mm"
        },
        "Ordnance QF 2-pounder": {
          "count": 12,
          "caliber": "40mm"
        }
      },
      "infantry": {},
      "vehicles": {}
    },
    "equipment_summary": {
      "total_tanks": 218,
      "total_artillery": 48,
      "total_at_guns": 36,
      "total_personnel": 14450
    }
  }
}