{
  "metadata": {
    "nation": "German",
    "quarter": "1941q1",
    "date": "1941-03-01",
    "unit_designation": "5 Leichte Division",
    "unit_type": "leichte Division (Light Division)",
    "organization_level": "division",
    "theater": "North Africa - Libya",
    "commander_name": "Generalmajor Johannes Streich",
    "commander_rank": "Generalmajor"
  },
  "narrative": {
    "title": "5 Leichte Division - 1941Q1",
    "date": "1941-03-01",
    "location": "North Africa - Libya",
    "nation": "German",
    "unit_type": "leichte Division (Light Division)",
    "situation": "German leichte Division (Light Division) deployed in North Africa - Libya during 1941Q1.",
    "objectives": "Mobile offensive operations in desert terrain",
    "axis_objective": "Maintain defensive positions and inflict maximum casualties on Allied forces.",
    "allied_objective": "Advance and secure strategic objectives while minimizing casualties.",
    "supply": {
      "fuel_days": 8,
      "ammunition_days": 7,
      "water_supply": 8,
      "supply_status": "Unknown",
      "notes": "Building up supply infrastructure, extended supply lines from Tripoli"
    },
    "weather": {
      "terrain": "Desert",
      "temperature": "Unknown",
      "visibility": "Clear",
      "seasonal_impacts": [],
      "environmental_challenges": []
    },
    "air_support": {
      "note": "No theater air summary available for this quarter"
    },
    "special_rules": [
      "Combined arms coordination (tanks, infantry, artillery)",
      "Rapid movement and exploitation",
      "Desert warfare adaptation"
    ]
  },
  "supply_states": {
    "fuel_days": 8,
    "ammunition_days": 7,
    "water_liters_per_day": 8,
    "food_days": 10,
    "notes": "Building up supply infrastructure, extended supply lines from Tripoli"
  },
  "environment": {},
  "air_support": null,
  "exported_at": "2025-10-29T07:13:10.507746",
  "source_file": "german_1941q1_5_leichte_division_toe.json",
  "exporter_version": "Phase 9A Enhanced (October 2025)"
}