{
  "quarter": "1940q3",
  "season": "Summer",
  "terrain_type": "Desert plateau, wadis, escarpments",
  "temperature_range_celsius": {
    "min": 20,
    "max": 42,
    "average": 32
  },
  "seasonal_impacts": [
    "Extreme heat during day",
    "Dust storms reduce visibility",
    "Clear skies favor air operations"
  ],
  "environmental_challenges": [
    "Water scarcity",
    "Engine overheating",
    "Sand damage to equipment"
  ],
  "visibility_km": 10,
  "precipitation": "none",
  "wind_speed_kph": 15
}