{
  "battlegroup_name": "3Rd Infantry Division",
  "nation": "American",
  "quarter": "1943q1",
  "total_points": 28916,
  "total_br": 498,
  "equipment": [
    {
      "name": "M2A1 105mm Howitzer",
      "count": 36,
      "type": "artillery",
      "battlegroup_stats": {
        "penetration": 1,
        "he_size": "medium",
        "points_each": 60,
        "points_total": 2160,
        "br_each": 3,
        "br_total": 108,
        "experience": "r",
        "mobility": "towed"
      },
      "original_data": {
        "caliber_mm": 105.0,
        "gun_pen_mm": 12
      }
    },
    {
      "name": "M1918 155mm Howitzer",
      "count": 12,
      "type": "artillery",
      "battlegroup_stats": {
        "penetration": 1,
        "he_size": "heavy",
        "points_each": 70,
        "points_total": 840,
        "br_each": 3,
        "br_total": 36,
        "experience": "r",
        "mobility": "towed"
      },
      "original_data": {
        "caliber_mm": 155.0,
        "gun_pen_mm": 14
      }
    },
    {
      "name": "M3 37mm AT Gun",
      "count": 57,
      "type": "anti_tank",
      "battlegroup_stats": {
        "penetration": 1,
        "he_size": "very_light",
        "points_each": 40,
        "points_total": 2280,
        "br_each": 2,
        "br_total": 114,
        "experience": "r",
        "mobility": "towed"
      },
      "original_data": {
        "caliber_mm": 37.0,
        "gun_pen_mm": 3
      }
    },
    {
      "name": "M3 Half-track",
      "count": 56,
      "type": "halftracks",
      "battlegroup_stats": {
        "points_each": 30,
        "points_total": 1680,
        "br_each": 1,
        "br_total": 56,
        "vehicle_type": "halftrack",
        "special_role": false
      }
    },
    {
      "name": "M2 Half-track",
      "count": 38,
      "type": "halftracks",
      "battlegroup_stats": {
        "points_each": 30,
        "points_total": 1140,
        "br_each": 1,
        "br_total": 38,
        "vehicle_type": "halftrack",
        "special_role": false
      }
    },
    {
      "name": "GMC CCKW 2.5-ton",
      "count": 765,
      "type": "trucks",
      "battlegroup_stats": {
        "points_each": 10,
        "points_total": 7650,
        "br_each": 0,
        "br_total": 0,
        "vehicle_type": "truck",
        "special_role": false
      }
    },
    {
      "name": "Dodge WC series",
      "count": 595,
      "type": "trucks",
      "battlegroup_stats": {
        "points_each": 10,
        "points_total": 5950,
        "br_each": 0,
        "br_total": 0,
        "vehicle_type": "truck",
        "special_role": false
      }
    },
    {
      "name": "Chevrolet G506",
      "count": 278,
      "type": "trucks",
      "battlegroup_stats": {
        "points_each": 10,
        "points_total": 2780,
        "br_each": 0,
        "br_total": 0,
        "vehicle_type": "truck",
        "special_role": false
      }
    },
    {
      "name": "Willys MB Jeep",
      "count": 154,
      "type": "trucks",
      "battlegroup_stats": {
        "points_each": 10,
        "points_total": 1540,
        "br_each": 0,
        "br_total": 0,
        "vehicle_type": "truck",
        "special_role": false
      }
    },
    {
      "name": "M8 Greyhound",
      "count": 54,
      "type": "armored_cars",
      "battlegroup_stats": {
        "points_each": 40,
        "points_total": 2160,
        "br_each": 1,
        "br_total": 54,
        "vehicle_type": "armored_car",
        "special_role": false
      }
    },
    {
      "name": "Harley-Davidson WLA",
      "count": 92,
      "type": "motorcycles",
      "battlegroup_stats": {
        "points_each": 8,
        "points_total": 736,
        "br_each": 1,
        "br_total": 92,
        "vehicle_type": "motorcycle",
        "special_role": false
      }
    }
  ],
  "exported_at": "2025-10-29T09:29:43.646951",
  "exporter_version": "Phase 9B BattleGroup (October 2025)"
}