{
  "scenario_name": "1942q2_german_1942q2_deutsches_afrika_vs_british_1942q2_1st_south_afric_squad",
  "quarter": "1942q2",
  "scenario_size": "squad",
  "points_target": 250,
  "generated_at": "2025-10-29T18:38:15.434917",
  "axis_force": {
    "nation": "german",
    "unit_name": "german_1942q2_deutsches_afrikakorps_toe",
    "experience": "veteran",
    "toe": {
      "tanks": {},
      "artillery": {
        "10.5cm leFH 18": {
          "count": 76,
          "caliber": "105mm"
        },
        "15cm sFH 18": {
          "count": 36,
          "caliber": "150mm"
        }
      },
      "anti_tank": {
        "5cm PaK 38": {
          "count": 48,
          "caliber": "50mm"
        },
        "7.62cm PaK 36(r)": {
          "count": 14,
          "caliber": "76.2mm"
        },
        "3.7cm PaK 35/36": {
          "count": 12,
          "caliber": "37mm"
        }
      },
      "infantry": {},
      "vehicles": {}
    },
    "equipment_summary": {
      "total_tanks": 228,
      "total_artillery": 112,
      "total_at_guns": 74,
      "total_personnel": 28650
    }
  },
  "allied_force": {
    "nation": "british",
    "unit_name": "british_1942q2_1st_south_african_division_toe",
    "experience": "veteran",
    "toe": {
      "tanks": {},
      "artillery": {
        "Ordnance QF 25-pounder": {
          "count": 96,
          "caliber": "87.6mm"
        }
      },
      "anti_tank": {
        "Ordnance QF 2-pounder": {
          "count": 52,
          "caliber": "40mm"
        },
        "Boys Anti-Tank Rifle": {
          "count": 4,
          "caliber": "13.9mm"
        }
      },
      "infantry": {},
      "vehicles": {}
    },
    "equipment_summary": {
      "total_tanks": 0,
      "total_artillery": 96,
      "total_at_guns": 56,
      "total_personnel": 17000
    }
  }
}