{
  "quarter": "1940q2",
  "axis_supply": {
    "fuel_days": 7,
    "ammunition_days": 7,
    "water_days": 7,
    "operational_radius_km": 35,
    "supply_status": "Adequate - Auto-transportable division deployed Libya-Tunisia border June 1940 during Italian invasion of France. Fuel reserves 4 days for partial motorization (enough to move portion of division), ammunition 7 days, water 24.5L/man/day (180,000L total / 7,350 personnel), food 10 days. Mixed motor/animal transport. Supply base: Misrata. Commander Vincenzo Della Mura.",
    "notes": "Standard operational supply levels"
  },
  "allied_supply": {
    "fuel_days": 7,
    "ammunition_days": 14,
    "water_days": 7,
    "operational_radius_km": 100,
    "supply_status": "Good - First Indian division deployed overseas in WWII, training at Fayed (Egypt) for desert operations in Q2 1940. Well-supplied from Egyptian base infrastructure. Fuel reserves 7 days for limited motorization (infantry division), ammunition adequate at 14 days for training exercises and defensive operations, water 10L/man/day for desert training (150,000L total / 15,000 personnel), food reserves 14 days. Mixed British-Indian composition (40% British, 60% Indian personnel). Supply base: Fayed/Ismailia with links to Alexandria and Suez. Commander Philip Neame (Feb-Aug 1940).",
    "notes": "Standard operational supply levels"
  }
}